distcrab/__init__.py
distcrab/__main__.py
distcrab/future.py
distcrab/logger.py
distcrab/main.paramiko.py
distcrab/main.py
distcrab/parser.py
distcrab/privateKeyArmored.asc
distcrab/publicKeyArmored.asc
distcrab-0.0.72.dist-info/METADATA
distcrab-0.0.72.dist-info/WHEEL
distcrab-0.0.72.dist-info/top_level.txt
distcrab-0.0.72.dist-info/RECORD
