Metadata-Version: 2.4
Name: distcrab
Version: 0.0.72
Requires-Dist: asyncssh
Requires-Dist: aiodav
Requires-Dist: aiofile
Requires-Dist: aiostream
Requires-Dist: gpg
Requires-Dist: humanize
Requires-Dist: dnspython
Requires-Dist: GitPython
Requires-Dist: httpx
Requires-Dist: pyOpenSSL
Dynamic: description
Dynamic: description-content-type
Dynamic: requires-dist
